forgecode/__init__.py
forgecode/builtins/schema_transform.py
forgecode/core/decorators.py
forgecode/core/execution_environment/execution_environment.py
forgecode/core/execution_environment/simple_execution.py
forgecode/core/forgecode.py
forgecode/core/llm/llm_client.py
forgecode/core/llm/openai_client.py
forgecode/core/llm/openrouter_client.py
forgecode/core/persistence/code_persistence.py
forgecode/core/persistence/forgecache.py
forgecode/core/prompts.py
forgecode/core/utils/data_limiter.py
forgecode/core/utils/dict_formatter.py
forgecode/core/utils/imports.py
forgecode/core/utils/json_schema_generator.py
forgecode/core/utils/normalize_args.py
forgecode-0.7.1.dist-info/LICENSE.txt
forgecode-0.7.1.dist-info/METADATA
forgecode-0.7.1.dist-info/WHEEL
forgecode-0.7.1.dist-info/RECORD
