Metadata-Version: 2.3
Name: forgecode
Version: 0.7.1
Summary: A Python library for runtime dynamic code generation and execution using LLMs—generating adaptive Python code from high-level goals, schemas, arguments, and functions.
License: MIT
Keywords: python,library,development,forgecode
Author: Filip Mihajlović
Author-email: filipmihajlovic@icloud.com
Requires-Python: >=3.8.1,<4.0
Classifier: Development Status :: 3 - Alpha
Classifier: Intended Audience :: Developers
Classifier: License :: OSI Approved :: MIT License
Classifier: Programming Language :: Python :: 3
Classifier: Programming Language :: Python :: 3.8
Classifier: Programming Language :: Python :: 3.9
Classifier: Programming Language :: Python :: 3.10
Classifier: Programming Language :: Python :: 3.11
Provides-Extra: pydantic
Requires-Dist: jsonschema (>=4.23.0,<5.0.0)
Requires-Dist: openai (>=1.65.2,<2.0.0)
Requires-Dist: pydantic (>=2.0.0,<3.0.0) ; extra == "pydantic"
Project-URL: Documentation, https://Cofyka.github.io/forgecode
Project-URL: Homepage, https://github.com/Cofyka/forgecode
Project-URL: Repository, https://github.com/Cofyka/forgecode
